django_river-3.2.2.dist-info/METADATA
django_river-3.2.2.dist-info/RECORD
django_river-3.2.2.dist-info/WHEEL
django_river-3.2.2.dist-info/top_level.txt
features/__init__.py
features/environment.py
features/steps/__init__.py
features/steps/basic_steps.py
features/steps/issue_tracking_steps.py
river/__init__.py
river/apps.py
river/config.py
river/signals.py
river/admin/__init__.py
river/admin/function_admin.py
river/admin/hook_admins.py
river/admin/transitionapprovalmeta.py
river/admin/transitionmeta.py
river/admin/workflow.py
river/core/__init__.py
river/core/classworkflowobject.py
river/core/instanceworkflowobject.py
river/core/riverobject.py
river/core/workflowregistry.py
river/driver/__init__.py
river/driver/mssql_driver.py
river/driver/orm_driver.py
river/driver/river_driver.py
river/migrations/0001_initial.py
river/migrations/__init__.py
river/models/__init__.py
river/models/base_model.py
river/models/factories.py
river/models/function.py
river/models/hook.py
river/models/on_approved_hook.py
river/models/on_complete_hook.py
river/models/on_transit_hook.py
river/models/state.py
river/models/transition.py
river/models/transitionapproval.py
river/models/transitionapprovalmeta.py
river/models/transitionmeta.py
river/models/workflow.py
river/models/fields/__init__.py
river/models/fields/state.py
river/models/managers/__init__.py
river/models/managers/rivermanager.py
river/models/managers/state.py
river/models/managers/transitionapproval.py
river/models/managers/transitionmetada.py
river/models/managers/workflowmetada.py
river/sql/mssql/get_available_approvals.sql
river/tests/__init__.py
river/tests/admin.py
river/tests/matchers.py
river/tests/test__app.py
river/tests/test__state_field.py
river/tests/core/__init__.py
river/tests/core/test__class_api.py
river/tests/core/test__instance_api.py
river/tests/hooking/__init__.py
river/tests/hooking/base_hooking_test.py
river/tests/hooking/test__approved_hooking.py
river/tests/hooking/test__completed_hooking.py
river/tests/hooking/test__transition_hooking.py
river/tests/models/__init__.py
