Metadata-Version: 2.1
Name: django-river
Version: 3.2.2
Summary: Django Workflow Library
Home-page: https://github.com/javrasya/django-river.git
Author: Ahmet DAL
Author-email: ceahmetdal@gmail.com
License: BSD
Platform: any
Requires-Dist: Django
Requires-Dist: django-mptt (==0.9.1)
Requires-Dist: django-cte (==1.1.4)
Requires-Dist: django-codemirror2 (==0.2)
